beanie_batteries_queue/__init__.py
beanie_batteries_queue/queue.py
beanie_batteries_queue/runner.py
beanie_batteries_queue/scheduled_task.py
beanie_batteries_queue/task.py
beanie_batteries_queue/worker.py
beanie_batteries_queue-0.4.0.dist-info/LICENSE
beanie_batteries_queue-0.4.0.dist-info/WHEEL
beanie_batteries_queue-0.4.0.dist-info/METADATA
beanie_batteries_queue-0.4.0.dist-info/RECORD
