Metadata-Version: 2.1
Name: beanie_batteries_queue
Version: 0.4.0
Summary: Advanced queue system for MongoDB with Beanie ODM
Keywords: mongodb,odm,orm,pydantic,mongo,async,python,beanie,queue,beanie-batteries-queue
Author-email: Roman Right <roman-right@protonmail.com>
Requires-Python: >=3.7,<4.0
Classifier: License :: OSI Approved :: Apache Software License
Classifier: Intended Audience :: Developers
Classifier: Programming Language :: Python :: 3.7
Classifier: Programming Language :: Python :: 3.8
Classifier: Programming Language :: Python :: 3.9
Classifier: Programming Language :: Python :: 3.10
Classifier: Programming Language :: Python :: 3.11
Classifier: Operating System :: OS Independent
Classifier: Topic :: Database
Classifier: Topic :: Software Development :: Libraries :: Python Modules
Classifier: Topic :: Software Development :: Object Brokering
Classifier: Topic :: System :: Distributed Computing
Classifier: Typing :: Typed
Requires-Dist: beanie>=1.23.4
Requires-Dist: pre-commit>=2.3.0 ; extra == "test"
Requires-Dist: pytest>=6.0.0 ; extra == "test"
Requires-Dist: pytest-asyncio>=0.21.0 ; extra == "test"
Requires-Dist: pytest-cov>=2.8.1 ; extra == "test"
Requires-Dist: dnspython>=2.1.0 ; extra == "test"
Requires-Dist: flake8>=3 ; extra == "test"
Requires-Dist: pyright>=0 ; extra == "test"
Requires-Dist: pydantic-settings>=2.0 ; extra == "test"
Project-URL: homepage, https://github.com/roman-right/beanie_batteries_queue
Project-URL: repository, https://github.com/roman-right/beanie_batteries_queue
Provides-Extra: test
